ImageGrabber/__init__.py
ImageGrabber/imageGrabber/__init__.py
ImageGrabber/imageGrabber/grabber.py
ImageResolver/__init__.py
ImageResolver/imageResolver/__init__.py
ImageResolver/imageResolver/resolver.py
JobHandler/__init__.py
JobHandler/jobHandler.py
JobHandler/managers/RegionURLManager.py
JobHandler/managers/__init__.py
LogHandler/__init__.py
LogHandler/logHandler.py
ManagerAPI/__init__.py
ManagerAPI/server.py
ManagerAPI/api/__init__.py
ManagerAPI/api/api.py
ManagerAPI/api/managers/__init__.py
ManagerAPI/api/managers/connection_manager.py
ManagerAPI/api/managers/job_manager.py
ManagerAPI/api/managers/state_manager.py
ManagerAPI/api/models/__init__.py
ManagerAPI/api/models/managedJob.py
ManagerAPI/api/routers/__init__.py
ManagerAPI/api/routers/auth.py
ManagerAPI/api/routers/jobs.py
VideoMaker/__init__.py
VideoMaker/videoMaker/__init__.py
VideoMaker/videoMaker/videomaker.py
VideoMaker/videoMaker/managers/__init__.py
VideoMaker/videoMaker/managers/video_manager.py
VideoUploader/__init__.py
VideoUploader/videoUploader/__init__.py
VideoUploader/videoUploader/uploader.py
VideoUploader/videoUploader/managers/__init__.py
VideoUploader/videoUploader/managers/upload_manager.py
tests/__init__.py
tests/test_RegionURLManager.py
tests/test_api.py
tests/test_jobhandler.py
tests/test_loghandler.py
tests/test_managedJob.py
tests/test_router_job.py
tests/test_state_manager.py
rootsweatherproject-1.0.41.dist-info/METADATA
rootsweatherproject-1.0.41.dist-info/WHEEL
rootsweatherproject-1.0.41.dist-info/entry_points.txt
rootsweatherproject-1.0.41.dist-info/top_level.txt
rootsweatherproject-1.0.41.dist-info/RECORD
