Metadata-Version: 2.4
Name: RootsWeatherProject
Version: 1.0.41
Summary: A package holding microservices to create video from compiled weather image data
Home-page: https://github.com/johncanthony/RootsWeatherProject
Author: John Anthony
Classifier: Development Status :: 3 - Alpha
Classifier: Intended Audience :: Developers
Classifier: License :: OSI Approved :: MIT License
Classifier: Programming Language :: Python :: 3.10
Classifier: Programming Language :: Python :: 3.12
Requires-Dist: pytest
Requires-Dist: fastapi
Requires-Dist: pydantic
Requires-Dist: uvicorn
Requires-Dist: httpx
Requires-Dist: redis
Requires-Dist: requests
Requires-Dist: beautifulsoup4
Requires-Dist: bs4
Requires-Dist: setuptools
Requires-Dist: ffmpeg-python
Requires-Dist: google_auth_oauthlib
Requires-Dist: google-api-python-client
Dynamic: author
Dynamic: classifier
Dynamic: description
Dynamic: description-content-type
Dynamic: home-page
Dynamic: requires-dist
Dynamic: summary
